PyQEA/__init__.py
PyQEA/qea.py
PyQEA/utils/__init__.py
PyQEA/utils/cost_functions.py
PyQEA-0.1.5.dist-info/LICENSE.md
PyQEA-0.1.5.dist-info/METADATA
PyQEA-0.1.5.dist-info/WHEEL
PyQEA-0.1.5.dist-info/top_level.txt
PyQEA-0.1.5.dist-info/RECORD
