Metadata-Version: 2.1
Name: PyQEA
Version: 0.1.5
Summary: General use optimizer for non-convex cost                functions with non-linear constraints
Home-page: https://github.com/ferwanguer/PyQEA
Author: Fernando Wanguemert
Author-email: f.wguerra@outlook.com
License: UNKNOWN
Platform: UNKNOWN
Classifier: Programming Language :: Python :: 3
Classifier: License :: OSI Approved :: MIT License
Classifier: Operating System :: OS Independent
Requires-Dist: numpy
